yamwapi/__init__.py
yamwapi/yamwapi.py
yamwapi/yamwapi_test.py
yamwapi-0.3.dist-info/LICENSE
yamwapi-0.3.dist-info/METADATA
yamwapi-0.3.dist-info/WHEEL
yamwapi-0.3.dist-info/top_level.txt
yamwapi-0.3.dist-info/RECORD
