Metadata-Version: 2.1
Name: yamwapi
Version: 0.3
Summary: A simple and modern library for interacting with the MediaWiki API. Use me to talk to Wikipedia.
Home-page: https://github.com/eggpi/yamwapi
Author: Guilherme Gonçalves
Author-email: guilherme.p.gonc@gmail.com
License: UNKNOWN
Download-URL: https://github.com/eggpi/yamwapi/archive/0.3.tar.gz
Keywords: wikipedia mediawiki
Platform: UNKNOWN
